wAsciiArt/Waa.py
wAsciiArt/__init__.py
wAsciiArt/__main__.py
wAsciiArt-1.1.dist-info/LICENSE
wAsciiArt-1.1.dist-info/METADATA
wAsciiArt-1.1.dist-info/WHEEL
wAsciiArt-1.1.dist-info/top_level.txt
wAsciiArt-1.1.dist-info/RECORD
