Metadata-Version: 2.1
Name: wAsciiArt
Version: 1.1
Summary: Provides ascii art representation of witrdotnet
Home-page: https://github.com/witrdotnet/wAsciiArt
Author: witrdotnet
Author-email: witr.net@gmail.com
License: UNKNOWN
Platform: UNKNOWN
Classifier: Programming Language :: Python
Classifier: Programming Language :: Python :: 2
Classifier: Programming Language :: Python :: 3
Classifier: License :: OSI Approved :: MIT License
Classifier: Operating System :: OS Independent
Requires-Python: >=2.0
